evaluation_lumo/__init__.py
evaluation_lumo/_version.py
evaluation_lumo/config.py
evaluation_lumo/evaluation.py
evaluation_lumo/metrics.py
evaluation_lumo/utils.py
evaluation_lumo/visualization.py
evaluation_lumo-0.1.9.dist-info/LICENSE
evaluation_lumo-0.1.9.dist-info/WHEEL
evaluation_lumo-0.1.9.dist-info/METADATA
evaluation_lumo-0.1.9.dist-info/RECORD
